hcjflex/__init__.py
hcjflex/build/__init__.py
hcjflex/build/build.py
hcjflex/contentcreation/__init__.py
hcjflex/contentcreation/createcontent.py
hcjflex/gui/__init__.py
hcjflex/gui/gui.py
hcjflex-0.0.1.dist-info/METADATA
hcjflex-0.0.1.dist-info/WHEEL
hcjflex-0.0.1.dist-info/entry_points.txt
hcjflex-0.0.1.dist-info/license_files/LICENSE
hcjflex-0.0.1.dist-info/RECORD
