Metadata-Version: 2.1
Name: hcjflex
Version: 0.0.1
Summary: hcjflex, native html/css/javascript gui library for python
Project-URL: Bug Tracker, https://github.com/acteam-ux/hcjflex/issues
Project-URL: Homepage, https://github.com/acteam-ux/hcjflex
Author-email: acteam <acteam1245@gmail.com>
License: Copyright (c) 2018 The Python Packaging Authority
Classifier: License :: OSI Approved :: MIT License
Classifier: Operating System :: OS Independent
Classifier: Programming Language :: Python :: 3
Requires-Python: >=3.7
